electrus/__init__.py
electrus/__version__.py
electrus/electron.py
electrus/asynchronous/__init__.py
electrus/asynchronous/core/__init__.py
electrus/asynchronous/core/client.py
electrus/asynchronous/core/collection.py
electrus/asynchronous/core/database.py
electrus/asynchronous/core/objects.py
electrus/asynchronous/core/transactions.py
electrus/asynchronous/partials/__init__.py
electrus/asynchronous/partials/delete.py
electrus/asynchronous/partials/find.py
electrus/asynchronous/partials/insert.py
electrus/asynchronous/partials/objectID.py
electrus/asynchronous/partials/operators.py
electrus/asynchronous/partials/result.py
electrus/asynchronous/partials/update.py
electrus/asynchronous/utils/__init__.py
electrus/asynchronous/utils/aggregation.py
electrus/asynchronous/utils/bulk.py
electrus/asynchronous/utils/compator.py
electrus/asynchronous/utils/distinct.py
electrus/exception/__init__.py
electrus/exception/base.py
electrus/recovery/__init__.py
electrus/recovery/format.py
electrus/recovery/recover.py
electrus/synchronous/__init__.py
electrus/synchronous/core/__init__.py
electrus/synchronous/core/client.py
electrus/synchronous/core/collection.py
electrus/synchronous/core/database.py
electrus/synchronous/core/transactions.py
electrus/synchronous/partials/__init__.py
electrus/synchronous/partials/delete.py
electrus/synchronous/partials/find.py
electrus/synchronous/partials/insert.py
electrus/synchronous/partials/objectID.py
electrus/synchronous/partials/operators.py
electrus/synchronous/partials/result.py
electrus/synchronous/partials/update.py
electrus/synchronous/utils/__init__.py
electrus/synchronous/utils/aggregation.py
electrus/synchronous/utils/bulk.py
electrus/synchronous/utils/compator.py
electrus/synchronous/utils/distinct.py
electrus-1.1.2.dist-info/LICENSE
electrus-1.1.2.dist-info/METADATA
electrus-1.1.2.dist-info/WHEEL
electrus-1.1.2.dist-info/top_level.txt
electrus-1.1.2.dist-info/RECORD
