Metadata-Version: 2.1
Name: electrus
Version: 1.1.2
Summary: Electrus is a lightweight asynchronous & synchronous database module designed for Python.
Home-page: https://github.com/embrake/electrus
Author: Pawan kumar
Author-email: embrakeproject@gmail.com
Keywords: database,async,asynchronous,synchronous,fast,lightweight,json
Classifier: Development Status :: 3 - Alpha
Classifier: Intended Audience :: Developers
Classifier: Topic :: Software Development :: Libraries
Classifier: License :: OSI Approved :: MIT License
Classifier: Programming Language :: Python :: 3
Classifier: Programming Language :: Python :: 3.6
Classifier: Programming Language :: Python :: 3.7
Classifier: Programming Language :: Python :: 3.8
Classifier: Programming Language :: Python :: 3.9
Requires-Python: >=3.6
License-File: LICENSE
